pts_tdk_lambda_psu/__init__.py
pts_tdk_lambda_psu/tdklambda_psu.py
pts_tdk_lambda_psu-0.0.11.dist-info/LICENSE.txt
pts_tdk_lambda_psu-0.0.11.dist-info/METADATA
pts_tdk_lambda_psu-0.0.11.dist-info/WHEEL
pts_tdk_lambda_psu-0.0.11.dist-info/top_level.txt
pts_tdk_lambda_psu-0.0.11.dist-info/RECORD
