Metadata-Version: 2.1
Name: pts-tdk-lambda-psu
Version: 0.0.11
Summary: TDK Lambda PSU Diagnostic Package
Home-page: https://gitlab.com/pass-testing-solutions/tdklambda_psu_interface
Author: Pass testing Solutions GmbH
Author-email: shuparna@pass-testing.de
License: MIT
Platform: UNKNOWN
Classifier: License :: OSI Approved :: MIT License
Classifier: Programming Language :: Python :: 3
Classifier: Programming Language :: Python :: 3.9
License-File: LICENSE.txt
Requires-Dist: RsInstrument (~=1.24.0.83)
Requires-Dist: pyvisa (==1.12.0)
Requires-Dist: pyvisa-py (==0.5.3)
